duelpy/__init__.py
duelpy/algorithms/__init__.py
duelpy/algorithms/active_ranking.py
duelpy/algorithms/algorithm.py
duelpy/algorithms/approximate_probability.py
duelpy/algorithms/beat_the_mean.py
duelpy/algorithms/binary_search_ranking.py
duelpy/algorithms/borda_ranking.py
duelpy/algorithms/copeland_confidence_bound.py
duelpy/algorithms/cw_rmed.py
duelpy/algorithms/double_thompson_sampling.py
duelpy/algorithms/exploreverify.py
duelpy/algorithms/interfaces.py
duelpy/algorithms/interleaved_filtering.py
duelpy/algorithms/kl_divergence_based_pac.py
duelpy/algorithms/knockout_tournament.py
duelpy/algorithms/mallows.py
duelpy/algorithms/merge_rucb.py
duelpy/algorithms/multisort.py
duelpy/algorithms/optmax.py
duelpy/algorithms/plackett_luce.py
duelpy/algorithms/preference_based_racing.py
duelpy/algorithms/relative_confidence_sampling.py
duelpy/algorithms/relative_ucb.py
duelpy/algorithms/rmed.py
duelpy/algorithms/savage.py
duelpy/algorithms/scalable_copeland_bandits.py
duelpy/algorithms/sequential_elimination.py
duelpy/algorithms/single_elimination_tournament.py
duelpy/algorithms/successive_elimination.py
duelpy/algorithms/winner_stays.py
duelpy/examples/__init__.py
duelpy/examples/decision.py
duelpy/experiments/__init__.py
duelpy/experiments/cli.py
duelpy/experiments/environments/__init__.py
duelpy/experiments/environments/hard_condorcet_matrix.py
duelpy/experiments/environments/mallows_model.py
duelpy/experiments/environments/plackett_luce_model.py
duelpy/feedback/__init__.py
duelpy/feedback/commandline_feedback.py
duelpy/feedback/feedback_mechanism.py
duelpy/feedback/matrix_feedback.py
duelpy/stats/__init__.py
duelpy/stats/confidence_radius.py
duelpy/stats/metrics.py
duelpy/stats/preference_estimate.py
duelpy/stats/preference_matrix.py
duelpy/util/__init__.py
duelpy/util/exceptions.py
duelpy/util/feedback_decorators.py
duelpy/util/heap.py
duelpy/util/sorting.py
duelpy/util/utility_functions.py
duelpy-1.0.0.dist-info/LICENSE
duelpy-1.0.0.dist-info/METADATA
duelpy-1.0.0.dist-info/WHEEL
duelpy-1.0.0.dist-info/top_level.txt
duelpy-1.0.0.dist-info/RECORD
