Metadata-Version: 2.1
Name: duelpy
Version: 1.0.0
Summary: Dueling Bandit Algorithms in Python
Home-page: https://gitlab.com/duelpy/duelpy
Author: The duelpy team
Author-email: contact.us.at@gitlab.invalid
License: UNKNOWN
Platform: UNKNOWN
Classifier: Programming Language :: Python :: 3
Classifier: License :: OSI Approved :: MIT License
Classifier: Operating System :: OS Independent
Requires-Python: >=3.7
Requires-Dist: numpy
Requires-Dist: seaborn
Requires-Dist: pandas
Requires-Dist: joblib
Requires-Dist: scipy
